lplateforme/__init__.py
lplateforme/plateforme.py
lplateforme-0.1.5.8.dist-info/METADATA
lplateforme-0.1.5.8.dist-info/WHEEL
lplateforme-0.1.5.8.dist-info/RECORD
